{
  "thumbnailUrl": "aaa.png",
  "backgroundColor": "#000000",
  "fabric": {
    "version": "6.0.0-rc1",
    "objects": [
      {
        "fontSize": 40,
        "fontWeight": "normal",
        "fontFamily": "Josefin Sans",
        "fontStyle": "normal",
        "lineHeight": 1.16,
        "text": "SSALOn",
        "charSpacing": 0,
        "textAlign": "center",
        "styles": [],
        "path": null,
        "pathStartOffset": 0,
        "pathSide": "left",
        "pathAlign": "baseline",
        "underline": false,
        "overline": false,
        "linethrough": false,
        "textBackgroundColor": "",
        "direction": "ltr",
        "type": "Text",
        "version": "6.0.0-rc1",
        "originX": "left",
        "originY": "top",
        "left": 70.5386,
        "top": 24,
        "width": 155.3599,
        "height": 45.2,
        "fill": "#FFFFFF",
        "stroke": null,
        "strokeWidth": 1,
        "strokeDashArray": null,
        "strokeLineCap": "butt",
        "strokeDashOffset": 0,
        "strokeLineJoin": "miter",
        "strokeUniform": false,
        "strokeMiterLimit": 4,
        "scaleX": 0.6293,
        "scaleY": 0.6293,
        "angle": 0,
        "flipX": false,
        "flipY": false,
        "opacity": 1,
        "shadow": null,
        "visible": true,
        "backgroundColor": "",
        "fillRule": "nonzero",
        "paintFirst": "fill",
        "globalCompositeOperation": "source-over",
        "skewX": 0,
        "skewY": 0
      },
      {
        "fontSize": 40,
        "fontWeight": "normal",
        "fontFamily": "Josefin Sans",
        "fontStyle": "normal",
        "lineHeight": 1.16,
        "text": "아주대학교에서 진행하는\n쌀롱 모임!\n\n하루만 보고 보지 않아도 되는\n일회성 모임!\n\n바로 지원하세요!!",
        "charSpacing": 0,
        "textAlign": "left",
        "styles": [],
        "pathStartOffset": 0,
        "pathSide": "left",
        "pathAlign": "baseline",
        "underline": false,
        "overline": false,
        "linethrough": false,
        "textBackgroundColor": "",
        "direction": "ltr",
        "type": "Text",
        "version": "6.0.0-rc1",
        "originX": "left",
        "originY": "top",
        "left": 36.18,
        "top": 155.82,
        "width": 465.7599,
        "height": 359.792,
        "fill": "#FFFFFF",
        "stroke": null,
        "strokeWidth": 1,
        "strokeDashArray": null,
        "strokeLineCap": "butt",
        "strokeDashOffset": 0,
        "strokeLineJoin": "miter",
        "strokeUniform": false,
        "strokeMiterLimit": 4,
        "scaleX": 0.6097,
        "scaleY": 0.6097,
        "angle": 0,
        "flipX": false,
        "flipY": false,
        "opacity": 1,
        "shadow": null,
        "visible": true,
        "backgroundColor": "",
        "fillRule": "nonzero",
        "paintFirst": "fill",
        "globalCompositeOperation": "source-over",
        "skewX": 0,
        "skewY": 0
      }
    ]
  }
}
